README.md
setup.py
shabam/__init__.py
shabam/__main__.py
shabam/colors.py
shabam/coverage.py
shabam/parse_reads.py
shabam/plot.py
shabam/plot_axis.py
shabam/plot_coverage.py
shabam/plot_gridlines.py
shabam/plot_reads.py
shabam/utils.py
shabam.egg-info/PKG-INFO
shabam.egg-info/SOURCES.txt
shabam.egg-info/dependency_links.txt
shabam.egg-info/entry_points.txt
shabam.egg-info/requires.txt
shabam.egg-info/top_level.txt