Metadata-Version: 2.1
Name: shabam
Version: 1.0.0
Summary: Easy sequence alignment plots
Home-page: UNKNOWN
Author: Daniel Rice
Author-email: daniel.rice@sanger.ac.uk
License: GPL
Platform: UNKNOWN
Classifier: Development Status :: 4 - Beta
Classifier: License :: OSI Approved :: GNU General Public License (GPL)
Classifier: Topic :: Scientific/Engineering :: Bio-Informatics
Classifier: Topic :: Scientific/Engineering :: Visualization
Requires-Python: >=3.6
